[
  {
    "title": "Annual GHG emissions from crops and livestock",
    "description": "Annual GHG emissions from crops and livestock.",
    "axisY": "Gt CO2e",
    "axisX": "year",
    "legend": [
      {
        "key": "Total GHG Agriculture",
        "inLegend": true,
        "type": "upper",
        "color": "hsl(300, 70%, 50%)"
      },
      {
        "key": "FAO Agric global",
        "type": "lower",
        "inLegend": true,
        "color": "black"
      },
      {
        "key": "Livestock CH4",
        "color": "#9b2226",
        "inGraph": true,
        "inLegend": true
      },
      {
        "key": "Livestock N2O",
        "color": "hsl(35, 70%, 40%)",
        "inGraph": true,
        "inLegend": true
      },
      {
        "key": "Crop N2O",
        "color": "#4d908e",
        "inGraph": true,
        "inLegend": true
      },
      {
        "key": "Crop CO2",
        "color": "hsl(60, 70%, 50%)",
        "inGraph": true,
        "inLegend": true
      }
    ],
    "data": [
      {
        "valueX": 2000,
        "Total GHG Agriculture": 4.302373886342893,
        "Livestock CH4": 1.916910229845479,
        "Livestock N2O": 0.6773245698127996,
        "Crop N2O": 0.713654956095964,
        "Crop CH4": 0.5040216072626451,
        "Crop CO2": 0.4904625233260038,
        "Biofuel": -0.012363886097520442
      },
      {
        "valueX": 2005,
        "Total GHG Agriculture": 4.56406371322236,
        "Livestock CH4": 2.024626095839002,
        "Livestock N2O": 0.7346221982780317,
        "Crop N2O": 0.7835792975605497,
        "Crop CH4": 0.505935081175252,
        "Crop CO2": 0.5153010403695233,
        "Biofuel": -0.02027423989837394
      },
      {
        "valueX": 2010,
        "Total GHG Agriculture": 4.890872031825676,
        "Livestock CH4": 2.1309105103911103,
        "Livestock N2O": 0.7921298396582349,
        "Crop N2O": 0.9308910742045908,
        "Crop CH4": 0.5066209160969669,
        "Crop CO2": 0.5303196914747738,
        "Biofuel": -0.1063528502023693
      },
      {
        "valueX": 2015,
        "Total GHG Agriculture": 5.294835036665838,
        "Livestock CH4": 2.336916567012891,
        "Livestock N2O": 0.8824045195107243,
        "Crop N2O": 0.9980330922637776,
        "Crop CH4": 0.5116913944480339,
        "Crop CO2": 0.5657894634304099,
        "Biofuel": -0.12432195215858638
      },
      {
        "valueX": 2020,
        "Total GHG Agriculture": 5.831828588814241,
        "Livestock CH4": 2.65797841368899,
        "Livestock N2O": 0.9944478189430381,
        "Crop N2O": 1.0519524822475126,
        "Crop CH4": 0.538045686352066,
        "Crop CO2": 0.5894041875826297,
        "Biofuel": -0.14717961268484883
      },
      {
        "valueX": 2025,
        "Total GHG Agriculture": 6.28545887516714,
        "Livestock CH4": 2.942025889839321,
        "Livestock N2O": 1.092010860603058,
        "Crop N2O": 1.0956121436790056,
        "Crop CH4": 0.5520810558808237,
        "Crop CO2": 0.6037289251649324,
        "Biofuel": -0.1644290374428516
      },
      {
        "valueX": 2030,
        "Total GHG Agriculture": 6.685926258077889,
        "Livestock CH4": 3.2197603597358344,
        "Livestock N2O": 1.1839363063521167,
        "Crop N2O": 1.1339631246978905,
        "Crop CH4": 0.5347927457917899,
        "Crop CO2": 0.6134737215002593,
        "Biofuel": -0.1644290374428516
      },
      {
        "valueX": 2035,
        "Total GHG Agriculture": 7.127580275789587,
        "Livestock CH4": 3.544325295478557,
        "Livestock N2O": 1.2654702165118215,
        "Crop N2O": 1.1877058062673986,
        "Crop CH4": 0.5110066242502508,
        "Crop CO2": 0.6190723332815601,
        "Biofuel": -0.1644290374428516
      },
      {
        "valueX": 2040,
        "Total GHG Agriculture": 7.471449428962267,
        "Livestock CH4": 3.803415372874122,
        "Livestock N2O": 1.3273324857618718,
        "Crop N2O": 1.2259212277634768,
        "Crop CH4": 0.4957569654880419,
        "Crop CO2": 0.6190233770747557,
        "Biofuel": -0.1644290374428516
      },
      {
        "valueX": 2045,
        "Total GHG Agriculture": 7.725594009646141,
        "Livestock CH4": 4.006325507598569,
        "Livestock N2O": 1.3773574238164854,
        "Crop N2O": 1.2463777345885085,
        "Crop CH4": 0.4819095911589442,
        "Crop CO2": 0.6136237524836349,
        "Biofuel": -0.1644290374428516
      },
      {
        "valueX": 2050,
        "Total GHG Agriculture": 7.8754381121943045,
        "Livestock CH4": 4.145256228799679,
        "Livestock N2O": 1.4095408358151904,
        "Crop N2O": 1.2512921763668505,
        "Crop CH4": 0.466134832827163,
        "Crop CO2": 0.603214038385422,
        "Biofuel": -0.1644290374428516,
        "targets": [
          {
            "value": 4,
            "byYear": 2050
          }
        ]
      }
    ],
    "keys": [
      "Livestock CH4",
      "Livestock N2O",
      "Crop N2O",
      "Crop CO2"
    ],
    "upperLower": true
  },
  {
    "title": "Average annual GHG emissions from land use change and peat oxidation.",
    "description": "Average annual GHG emissions from land use change and peat oxidation",
    "axisY": "Gt CO2e",
    "axisX": "year",
    "legend": [
      {
        "key": "FAO LU global",
        "color": "black",
        "type": "lower",
        "inLegend": true
      },
      {
        "key": "Total GHG Land",
        "color": "hsl(300, 70%, 50%)",
        "type": "upper",
        "inLegend": true
      },
      {
        "key": "Forest loss",
        "color": "hsl(120, 70%, 25%)",
        "inGraph": true,
        "inLegend": true
      },
      {
        "key": "Other LUC",
        "color": "hsl(60, 70%, 50%)",
        "inGraph": true,
        "inLegend": true
      },
      {
        "key": "Sequestration",
        "color": "#4d908e",
        "inGraph": true,
        "inLegend": true
      },
      {
        "key": "Peat",
        "color": "#9b2226",
        "inGraph": true,
        "inLegend": true
      }
    ],
    "data": [
      {
        "valueX": 2000,
        "Total GHG Land": 0.08872204763598997,
        "Forest Loss": 0,
        "Other LUC": 0.02343696153846154,
        "Sequestration": 0.06059526923076923,
        "Peat": 0.0046898168667591925
      },
      {
        "valueX": 2005,
        "Total GHG Land": 1.14641892283564,
        "Forest Loss": 0.579517377596859,
        "Other LUC": 0.17901597092923005,
        "Sequestration": -0.08226361024227913,
        "Peat": 0.04257505578721639
      },
      {
        "valueX": 2010,
        "Total GHG Land": 0.9467794431719981,
        "Forest Loss": 0.6638599528887332,
        "Other LUC": 0.18152444697531367,
        "Sequestration": -0.14659223904744464,
        "Peat": 0.09127526658836728
      },
      {
        "valueX": 2015,
        "Total GHG Land": 1.5053623979132875,
        "Forest Loss": 0.8557780055412487,
        "Other LUC": 0.45106543837672963,
        "Sequestration": -0.19277704977033486,
        "Peat": 0.11264913507855893
      },
      {
        "valueX": 2020,
        "Total GHG Land": 2.028932751686269,
        "Forest Loss": 1.3562890905703147,
        "Other LUC": 0.4437257562080166,
        "Sequestration": -0.24284148348399007,
        "Peat": 0.14703953035724626
      },
      {
        "valueX": 2025,
        "Total GHG Land": 1.4368058945388427,
        "Forest Loss": 1.033338479930926,
        "Other LUC": 0.33124956931855687,
        "Sequestration": -0.31737376014708485,
        "Peat": 0.1791173573695091
      },
      {
        "valueX": 2030,
        "Total GHG Land": 1.133675139207642,
        "Forest Loss": 0.8463451940736804,
        "Other LUC": 0.3710066123390723,
        "Sequestration": -0.3741069965770584,
        "Peat": 0.2075085346058982
      },
      {
        "valueX": 2035,
        "Total GHG Land": 0.948516388036115,
        "Forest Loss": 0.6402831600019055,
        "Other LUC": 0.40398195343763743,
        "Sequestration": -0.4311790255775418,
        "Peat": 0.21903177099906893
      },
      {
        "valueX": 2040,
        "Total GHG Land": 0.7388786031541701,
        "Forest Loss": 0.5685500178010883,
        "Other LUC": 0.4355520988453455,
        "Sequestration": -0.5042007261642086,
        "Peat": 0.22921608725772025
      },
      {
        "valueX": 2045,
        "Total GHG Land": 0.4586225918012932,
        "Forest Loss": 0.5509547096423327,
        "Other LUC": 0.25199825205923765,
        "Sequestration": -0.5938103854607241,
        "Peat": 0.23886546377653103
      },
      {
        "valueX": 2050,
        "Total GHG Land": 0.12344162092204615,
        "Forest Loss": 0.5388250544305097,
        "Other LUC": 0.08487884975907276,
        "Sequestration": -0.7595808725465232,
        "Peat": 0.24777599508085224,
        "targets": [
          {
            "value": 0,
            "byYear": 2050
          }
        ]
      }
    ],
    "keys": [
      "Forest loss",
      "Other LUC",
      "Sequestration",
      "Peat"
    ],
    "withTarget": true,
    "upperLower": true
  },
  {
    "title": "GHG emissions from crops and livestock in Gt CO2e by country",
    "description": "GHG emissions from crops and livestock in Gt CO2e by country",
    "axisY": "Gt CO2e",
    "axisX": "year",
    "legend": [],
    "data": [
      {
        "valueX": 2000,
        "BRA": 0.25705643231111797,
        "IND": 0.602981,
        "AUS": 0.0952290786470507,
        "ARG": 0.06972303530373511,
        "RWA": 0.000799943869619001,
        "DEU": 0.06622918521792749,
        "CAN": 0.057002746779210904,
        "MEX": 0.06637653605954899,
        "ZAF": 0.0340714515645573,
        "CHN": 0.649442363735829,
        "NOR": 0.00488422610980395,
        "ETH": 0.0466800116585221,
        "R_OEU": 0.40923671434148,
        "R_SSA": 0.24387189467760398,
        "R_CSA": 0.12914455579512,
        "R_NEU": 0.130911774417884,
        "R_NMC": 0.299612260311861,
        "R_ASP": 0.415926472085891,
        "RUS": 0.1138182004399,
        "MYS": 0.00801181318035834,
        "SWE": 0.00712409057569434,
        "USA": 0.371534408050776,
        "FIN": 0.00660941687250102,
        "COL": 0.0502847763847798,
        "IDN": 0.10874365400172399,
        "GBR": 0.0447039578528751
      },
      {
        "valueX": 2005,
        "BRA": 0.306787212458659,
        "IND": 0.6314002000000001,
        "AUS": 0.0910158120129203,
        "ARG": 0.0861886664494818,
        "RWA": 0.00110789927553341,
        "DEU": 0.0609356845118185,
        "CAN": 0.0597226873068676,
        "MEX": 0.0680296260019201,
        "ZAF": 0.0337146122499973,
        "CHN": 0.705429165296576,
        "NOR": 0.00483156524451241,
        "ETH": 0.0630612613688508,
        "R_OEU": 0.393279627391657,
        "R_SSA": 0.270562954390357,
        "R_CSA": 0.13813212883371198,
        "R_NEU": 0.122858652404521,
        "R_NMC": 0.349111027428041,
        "R_ASP": 0.42890529510237296,
        "RUS": 0.09856945092257201,
        "MYS": 0.010331128723011201,
        "SWE": 0.006678152447276559,
        "USA": 0.390329611013863,
        "FIN": 0.0067586279440353,
        "COL": 0.056487654437426,
        "IDN": 0.11953755342934301,
        "GBR": 0.0400232166786593
      },
      {
        "valueX": 2010,
        "BRA": 0.311267513769514,
        "IND": 0.6549471,
        "AUS": 0.0785441622665672,
        "ARG": 0.0763159480084798,
        "RWA": 0.00159506565412349,
        "DEU": 0.0632105966627671,
        "CAN": 0.061257200967205896,
        "MEX": 0.06990308389946741,
        "ZAF": 0.0348032148901557,
        "CHN": 0.8205945191876239,
        "NOR": 0.0047689554982612405,
        "ETH": 0.0798315715528673,
        "R_OEU": 0.378057942173631,
        "R_SSA": 0.31246672105911,
        "R_CSA": 0.14957452011983302,
        "R_NEU": 0.12463307366354501,
        "R_NMC": 0.406534518382053,
        "R_ASP": 0.461256706617172,
        "RUS": 0.0956134745597357,
        "MYS": 0.0165391813947146,
        "SWE": 0.00606330826847893,
        "USA": 0.348420875634317,
        "FIN": 0.006604289664313159,
        "COL": 0.0590081934962555,
        "IDN": 0.124939314030397,
        "GBR": 0.037768130202718506
      },
      {
        "valueX": 2015,
        "BRA": 0.327975757794628,
        "IND": 0.7830773000000001,
        "AUS": 0.0821166071277942,
        "ARG": 0.0783159884570446,
        "RWA": 0.00199085026844758,
        "DEU": 0.061646435617687,
        "CAN": 0.0697095060497267,
        "MEX": 0.0737037419541124,
        "ZAF": 0.0380289001864726,
        "CHN": 0.8394840921940451,
        "NOR": 0.004884800393343771,
        "ETH": 0.101926953144405,
        "R_OEU": 0.39341558066891996,
        "R_SSA": 0.358231759350907,
        "R_CSA": 0.15557442113651299,
        "R_NEU": 0.13647918106751,
        "R_NMC": 0.47180772160517304,
        "R_ASP": 0.468898518863949,
        "RUS": 0.105617374014189,
        "MYS": 0.0186352538624568,
        "SWE": 0.00643068192964638,
        "USA": 0.346811744709886,
        "FIN": 0.0074125399133388396,
        "COL": 0.0598249668759325,
        "IDN": 0.138424557624937,
        "GBR": 0.0400878496961867
      },
      {
        "valueX": 2020,
        "BRA": 0.34460142019388,
        "IND": 0.9127816,
        "AUS": 0.0858937941694026,
        "ARG": 0.0816201606476497,
        "RWA": 0.00234667287318111,
        "DEU": 0.060357832873024896,
        "CAN": 0.0761465990378573,
        "MEX": 0.0738060793481258,
        "ZAF": 0.0382325368899743,
        "CHN": 0.846647732731887,
        "NOR": 0.00483272578850454,
        "ETH": 0.12331934488106999,
        "R_OEU": 0.407254326479842,
        "R_SSA": 0.499539095689808,
        "R_CSA": 0.17186012827904099,
        "R_NEU": 0.14802628758671,
        "R_NMC": 0.5236711806865979,
        "R_ASP": 0.545729257628897,
        "RUS": 0.108442403184661,
        "MYS": 0.0202463055882859,
        "SWE": 0.006699559809636941,
        "USA": 0.3478816456972,
        "FIN": 0.00742863666591391,
        "COL": 0.0613861053137263,
        "IDN": 0.144756603117006,
        "GBR": 0.041140940967508796
      },
      {
        "valueX": 2025,
        "BRA": 0.359816172099707,
        "IND": 1.0438849000000001,
        "AUS": 0.0889515244000135,
        "ARG": 0.0834495788470246,
        "RWA": 0.00257611126370595,
        "DEU": 0.0593939108610952,
        "CAN": 0.0821946517242239,
        "MEX": 0.0739188598017689,
        "ZAF": 0.038604899041957505,
        "CHN": 0.8572179661856639,
        "NOR": 0.004856409861987219,
        "ETH": 0.14170336882468001,
        "R_OEU": 0.421397597498234,
        "R_SSA": 0.6122787172030599,
        "R_CSA": 0.179920964288314,
        "R_NEU": 0.159045830001733,
        "R_NMC": 0.57255116200676,
        "R_ASP": 0.59133839390804,
        "RUS": 0.10954107351831201,
        "MYS": 0.021167603241274598,
        "SWE": 0.00694506878399294,
        "USA": 0.340675333829006,
        "FIN": 0.007466771012897231,
        "COL": 0.0626173539332256,
        "IDN": 0.157957818097673,
        "GBR": 0.0415577974899387
      },
      {
        "valueX": 2030,
        "BRA": 0.3802109772676,
        "IND": 1.139759,
        "AUS": 0.08949178878919069,
        "ARG": 0.0851397955433215,
        "RWA": 0.00259040530529431,
        "DEU": 0.0579234077414095,
        "CAN": 0.08847556736794379,
        "MEX": 0.0738758785432964,
        "ZAF": 0.038282999069376204,
        "CHN": 0.870593673429478,
        "NOR": 0.0048513332533310005,
        "ETH": 0.155122277614632,
        "R_OEU": 0.436951200081646,
        "R_SSA": 0.7362245357488411,
        "R_CSA": 0.18497941386081201,
        "R_NEU": 0.170058976411147,
        "R_NMC": 0.617331543126382,
        "R_ASP": 0.630408342379621,
        "RUS": 0.109559612647858,
        "MYS": 0.019629289533566803,
        "SWE": 0.00716749948977382,
        "USA": 0.340081161444227,
        "FIN": 0.00741162477834282,
        "COL": 0.0634525628007883,
        "IDN": 0.170750153305824,
        "GBR": 0.0411742011013361
      },
      {
        "valueX": 2035,
        "BRA": 0.402021114252806,
        "IND": 1.3030041,
        "AUS": 0.0901971443009799,
        "ARG": 0.0858023445935479,
        "RWA": 0.00269374866459745,
        "DEU": 0.056057727786643606,
        "CAN": 0.093320946726163,
        "MEX": 0.073686985094867,
        "ZAF": 0.0372853463424357,
        "CHN": 0.885251501968667,
        "NOR": 0.004840126351402269,
        "ETH": 0.163113107665629,
        "R_OEU": 0.451883696881739,
        "R_SSA": 0.869512700725678,
        "R_CSA": 0.18718893218337002,
        "R_NEU": 0.181042935675616,
        "R_NMC": 0.658736730470407,
        "R_ASP": 0.6529096393069861,
        "RUS": 0.108961769068705,
        "MYS": 0.0189214149153638,
        "SWE": 0.007399991790010931,
        "USA": 0.336776422276676,
        "FIN": 0.007363122940623821,
        "COL": 0.0631623278536131,
        "IDN": 0.181232564161981,
        "GBR": 0.040784796348224295
      },
      {
        "valueX": 2040,
        "BRA": 0.406521280958163,
        "IND": 1.4287874999999999,
        "AUS": 0.09016696217851261,
        "ARG": 0.0853648391255001,
        "RWA": 0.00273551779274832,
        "DEU": 0.0538552321296457,
        "CAN": 0.0979104349003228,
        "MEX": 0.0733761924534538,
        "ZAF": 0.0359024646315235,
        "CHN": 0.900523761625507,
        "NOR": 0.0048234295948982,
        "ETH": 0.153041697688472,
        "R_OEU": 0.45803013290726396,
        "R_SSA": 1.0085402570139101,
        "R_CSA": 0.18639913522336599,
        "R_NEU": 0.19168358134018398,
        "R_NMC": 0.696101709592219,
        "R_ASP": 0.667165213450123,
        "RUS": 0.10803475257878399,
        "MYS": 0.0192992665209301,
        "SWE": 0.00762007258986031,
        "USA": 0.33262334057145304,
        "FIN": 0.00728949711862856,
        "COL": 0.0623608781837177,
        "IDN": 0.188473197179594,
        "GBR": 0.040390044170641196
      },
      {
        "valueX": 2045,
        "BRA": 0.404724479949233,
        "IND": 1.5080938000000002,
        "AUS": 0.0905476580532056,
        "ARG": 0.08401059972659511,
        "RWA": 0.00271848141532417,
        "DEU": 0.0512065408971481,
        "CAN": 0.10158753048257001,
        "MEX": 0.072848831910216,
        "ZAF": 0.033624016174744704,
        "CHN": 0.904601509191335,
        "NOR": 0.004802734834827241,
        "ETH": 0.141373890045976,
        "R_OEU": 0.45823301173980097,
        "R_SSA": 1.1493409852810201,
        "R_CSA": 0.18278762768012502,
        "R_NEU": 0.201779224215748,
        "R_NMC": 0.728426559127845,
        "R_ASP": 0.674794363353745,
        "RUS": 0.106666627458317,
        "MYS": 0.0193617359981167,
        "SWE": 0.00781226186096256,
        "USA": 0.32953229979451,
        "FIN": 0.0071872212466082,
        "COL": 0.061725930779416405,
        "IDN": 0.19334803477511697,
        "GBR": 0.0400290162107865
      },
      {
        "valueX": 2050,
        "BRA": 0.39754034027055,
        "IND": 1.550552,
        "AUS": 0.0891958867410457,
        "ARG": 0.0820527937931232,
        "RWA": 0.0026497480571341,
        "DEU": 0.0482101513159253,
        "CAN": 0.105161695246613,
        "MEX": 0.0710779706981745,
        "ZAF": 0.0308511011624679,
        "CHN": 0.8824280300042611,
        "NOR": 0.00477912066008791,
        "ETH": 0.12935153754769801,
        "R_OEU": 0.458255460871978,
        "R_SSA": 1.2876637208330102,
        "R_CSA": 0.17658763553277898,
        "R_NEU": 0.20402259622388,
        "R_NMC": 0.7550156932636449,
        "R_ASP": 0.67393207822351,
        "RUS": 0.10510306107935201,
        "MYS": 0.0191073473404131,
        "SWE": 0.00800032588576914,
        "USA": 0.325830250041577,
        "FIN": 0.00707339882747493,
        "COL": 0.0607337215174952,
        "IDN": 0.19617070876325102,
        "GBR": 0.0396627008502363
      }
    ],
    "keys": [
      "ARG",
      "AUS",
      "BRA",
      "CAN",
      "CHN",
      "COL",
      "DEU",
      "ETH",
      "FIN",
      "GBR",
      "IDN",
      "IND",
      "MEX",
      "MYS",
      "NOR",
      "RUS",
      "RWA",
      "SWE",
      "USA",
      "ZAF",
      "R_ASP",
      "R_CSA",
      "R_NEU",
      "R_NMC",
      "R_OEU",
      "R_SSA"
    ],
    "byCountry": true,
    "byMultipleCountry": true
  },
  {
    "title": "Average annual GHG emissions from land use change and peat oxidation in Gt CO2e by country.",
    "description": "Average annual GHG emissions from land use change and peat oxidation in Gt CO2e by country.",
    "axisY": "Gt CO2e",
    "axisX": "year",
    "legend": [],
    "data": [
      {
        "valueX": 2000,
        "BRA": 0,
        "IND": 0.2184838,
        "AUS": 0,
        "ARG": 0,
        "RWA": 0,
        "DEU": 0,
        "CAN": 0,
        "MEX": 0,
        "ZAF": 0,
        "CHN": 0,
        "NOR": 0,
        "ETH": 0,
        "R_OEU": 0,
        "R_SSA": 0,
        "R_CSA": 0,
        "R_NEU": 0,
        "R_NMC": 0,
        "R_ASP": 0,
        "RUS": 0,
        "MYS": 0,
        "SWE": 0,
        "USA": 0,
        "FIN": 0.0121935238535739,
        "COL": 0,
        "IDN": 0,
        "GBR": 0
      },
      {
        "valueX": 2005,
        "BRA": 1.23521414976444,
        "IND": 0.1840018,
        "AUS": -0.006798779631420259,
        "ARG": 0.0847180901273419,
        "RWA": 0.0003543040525852,
        "DEU": 0.0116097551122587,
        "CAN": 0.0036910145555185,
        "MEX": 0.0144737480609986,
        "ZAF": -0.0159486545623306,
        "CHN": 0.0102222788200456,
        "NOR": 0.000146764337076038,
        "ETH": 0.014595306183436399,
        "R_OEU": 0.00992943941307514,
        "R_SSA": 0.7849626017469721,
        "R_CSA": 0.16476925099071701,
        "R_NEU": 0.026713990076679798,
        "R_NMC": 0.0299293001423244,
        "R_ASP": -0.039769677848927404,
        "RUS": -0.023354723867626197,
        "MYS": 0.0742217882882782,
        "SWE": 0.000236253633885009,
        "USA": 0.0113717134666215,
        "FIN": 0.0137791500293852,
        "COL": 0.00206473952114757,
        "IDN": 0.388394360759361,
        "GBR": 0.00116123620082069
      },
      {
        "valueX": 2010,
        "BRA": 0.452723601104752,
        "IND": 0.1911662,
        "AUS": -0.0250542950289801,
        "ARG": 0.179986456339501,
        "RWA": 0.0006205558052434749,
        "DEU": 0.00820276015958985,
        "CAN": 0.0375124420696956,
        "MEX": 0.0210958230358413,
        "ZAF": -0.000803780997620238,
        "CHN": -0.11351179740965,
        "NOR": 0.000214928084084319,
        "ETH": 0.0066163348426408,
        "R_OEU": 0.00711511213777609,
        "R_SSA": 0.3956485880843,
        "R_CSA": 0.5781521623426059,
        "R_NEU": 0.0244151419535628,
        "R_NMC": -0.00249601376491055,
        "R_ASP": 0.099774143197237,
        "RUS": -0.013220483312574,
        "MYS": 0.06466245775953029,
        "SWE": 0.000747243788593536,
        "USA": -0.0317733144957751,
        "FIN": 0.0113592119963223,
        "COL": -0.0102475824854524,
        "IDN": 0.573033755601767,
        "GBR": 0.0056869014391148194
      },
      {
        "valueX": 2015,
        "BRA": 0.785707874084533,
        "IND": 0.2547301,
        "AUS": -0.0357137142577652,
        "ARG": 0.07097631039314391,
        "RWA": -0.000408064000216819,
        "DEU": -0.00343253733197637,
        "CAN": 0.202345759485077,
        "MEX": 0.088319751422427,
        "ZAF": 0.018620640009458,
        "CHN": 0.318746399210533,
        "NOR": 0.0000694669437335315,
        "ETH": 0.0258841317827813,
        "R_OEU": 0.0221133253167711,
        "R_SSA": 0.719059506972253,
        "R_CSA": 0.43141363807226996,
        "R_NEU": 0.0445530062166445,
        "R_NMC": -0.0342056617844587,
        "R_ASP": -0.0122958252322469,
        "RUS": 0.0210249086378063,
        "MYS": 0.189211659858692,
        "SWE": 0.000471977659299321,
        "USA": 0.0640703797062626,
        "FIN": 0.014960350731464199,
        "COL": -0.00966275476439785,
        "IDN": 0.725493207075408,
        "GBR": 0.011888398367051
      },
      {
        "valueX": 2020,
        "BRA": 0.8779703739633581,
        "IND": 0.3111112,
        "AUS": -0.033669404411882396,
        "ARG": 0.100624158757609,
        "RWA": 0.000364130030191268,
        "DEU": -0.00346883897513185,
        "CAN": 0.152660495560703,
        "MEX": 0.0050173819712928,
        "ZAF": -0.014834828379470099,
        "CHN": 0.14997537628253,
        "NOR": 0.0000455133754304787,
        "ETH": 0.0281040773234328,
        "R_OEU": 0.00872921831695876,
        "R_SSA": 1.11247887832914,
        "R_CSA": 1.18024062617789,
        "R_NEU": 0.0280534871162469,
        "R_NMC": -0.00171466485174823,
        "R_ASP": 0.10318777447638,
        "RUS": -0.00894364406352382,
        "MYS": 0.124633819050781,
        "SWE": 0.00102978021423994,
        "USA": 0.059859304492599595,
        "FIN": 0.012612972341287101,
        "COL": 0.00122687431593535,
        "IDN": 1.07523774442761,
        "GBR": 0.004693348542438471
      },
      {
        "valueX": 2025,
        "BRA": 0.547927500723207,
        "IND": 0.044174399999999996,
        "AUS": -0.0367127392312945,
        "ARG": 0.0482843064442331,
        "RWA": -0.000887770044661458,
        "DEU": -0.004790918584996229,
        "CAN": 0.142813366110773,
        "MEX": 0.00494224576400974,
        "ZAF": -0.0127537799899123,
        "CHN": 0.0829456940183766,
        "NOR": 0.000045700571546054,
        "ETH": 0.0224373801129983,
        "R_OEU": 0.00820962040904471,
        "R_SSA": 1.04553433444669,
        "R_CSA": 0.5723557411961611,
        "R_NEU": 0.0235092788504847,
        "R_NMC": -0.00196258319251586,
        "R_ASP": 0.048913391549749906,
        "RUS": -0.0211038053763942,
        "MYS": 0.106255521591031,
        "SWE": 0.0011102010755711,
        "USA": -0.00772542706348773,
        "FIN": 0.0129265604171549,
        "COL": -0.00753109289080879,
        "IDN": 1.1124152377541099,
        "GBR": 0.00436296113992004
      },
      {
        "valueX": 2030,
        "BRA": 0.17944263563176402,
        "IND": -0.025464200000000003,
        "AUS": -0.0445512718265296,
        "ARG": 0.0107752698292666,
        "RWA": -0.00174127783442755,
        "DEU": -0.00544491961601775,
        "CAN": 0.146139889868306,
        "MEX": 0.00664814313972096,
        "ZAF": -0.0242083840933086,
        "CHN": 0.167127783070748,
        "NOR": 0.0000428070693312043,
        "ETH": 0.0153913374978688,
        "R_OEU": 0.009829541772981029,
        "R_SSA": 1.07022393275693,
        "R_CSA": 0.33592813705134,
        "R_NEU": 0.0229916060455757,
        "R_NMC": -0.00009308575909640091,
        "R_ASP": 0.00812562242850673,
        "RUS": -0.028295068179342197,
        "MYS": -0.0009919757074394629,
        "SWE": 0.00110854262714527,
        "USA": -0.0145010015197579,
        "FIN": 0.0125375799113764,
        "COL": -0.015673836733765302,
        "IDN": 1.11976246270781,
        "GBR": 0.00244509180088314
      },
      {
        "valueX": 2035,
        "BRA": 0.276153201702181,
        "IND": -0.037443199999999996,
        "AUS": -0.050394851207312,
        "ARG": -0.006920158732325351,
        "RWA": -0.00169751899772953,
        "DEU": -0.00628194735434903,
        "CAN": 0.115329712246848,
        "MEX": 0.008807690841413219,
        "ZAF": -0.0398786215784109,
        "CHN": 0.216451264070282,
        "NOR": 0.000036329843022927905,
        "ETH": 0.00749791996473543,
        "R_OEU": 0.00905612310581357,
        "R_SSA": 1.11622635028649,
        "R_CSA": 0.125939721857224,
        "R_NEU": 0.0241433791881321,
        "R_NMC": 0.00529789958529389,
        "R_ASP": -0.0435329515277507,
        "RUS": -0.0318558558969419,
        "MYS": -0.010801365608343398,
        "SWE": 0.0012079863589037501,
        "USA": -0.0258810187869525,
        "FIN": 0.0124382843973566,
        "COL": -0.0250248682414386,
        "IDN": 0.827857742450586,
        "GBR": -0.000588639072829389
      },
      {
        "valueX": 2040,
        "BRA": -0.0682208034498228,
        "IND": -0.0215628,
        "AUS": -0.055293755599597504,
        "ARG": -0.022051376116245698,
        "RWA": -0.00181544648143502,
        "DEU": -0.00732374965322491,
        "CAN": 0.118250676149756,
        "MEX": 0.0110089736521541,
        "ZAF": -0.060624163221897,
        "CHN": 0.225440392121436,
        "NOR": 0.0000289848482088821,
        "ETH": -0.00476420929648045,
        "R_OEU": 0.00865270140584912,
        "R_SSA": 1.10906862797955,
        "R_CSA": -0.00451086009294215,
        "R_NEU": 0.0229428859047363,
        "R_NMC": 0.0146538146904167,
        "R_ASP": -0.0504370419115956,
        "RUS": -0.0357656289305096,
        "MYS": -0.00644433960292742,
        "SWE": 0.00115986971676704,
        "USA": -0.0334956866793506,
        "FIN": 0.0123096925043289,
        "COL": -0.038780113279450495,
        "IDN": 0.8094266125874889,
        "GBR": -0.000768889044370572
      },
      {
        "valueX": 2045,
        "BRA": -0.120545229846306,
        "IND": -0.0067719,
        "AUS": -0.0573619019742632,
        "ARG": -0.0408397039790283,
        "RWA": -0.00193062139633207,
        "DEU": -0.008931482734046559,
        "CAN": 0.104215507378037,
        "MEX": 0.0131126229121072,
        "ZAF": -0.0859204501883922,
        "CHN": -0.21810824152174002,
        "NOR": 0.0000226640648419849,
        "ETH": -0.00596230830849312,
        "R_OEU": -0.0100866904812126,
        "R_SSA": 1.07743411115959,
        "R_CSA": -0.025120010293222802,
        "R_NEU": 0.0205962976847451,
        "R_NMC": 0.0037340588748531597,
        "R_ASP": -0.059471916276811004,
        "RUS": -0.041121931487391,
        "MYS": -0.00951483086909574,
        "SWE": 0.00101502694640371,
        "USA": -0.103849971830074,
        "FIN": 0.012134032790086098,
        "COL": -0.0487063594713706,
        "IDN": 0.805347106546389,
        "GBR": -0.000949139015911755
      },
      {
        "valueX": 2050,
        "BRA": -0.186965054395295,
        "IND": -0.000111199999999998,
        "AUS": -0.0644943500572666,
        "ARG": -0.06264912913157,
        "RWA": -0.0021261071368237202,
        "DEU": -0.0108519037604091,
        "CAN": 0.11399768543851001,
        "MEX": 0.0141411200030816,
        "ZAF": -0.127438311178149,
        "CHN": -0.808465230489148,
        "NOR": 0.0000180308869240711,
        "ETH": -0.0059576449482607406,
        "R_OEU": -0.0228010694463857,
        "R_SSA": 1.04068008757316,
        "R_CSA": -0.0588991681807916,
        "R_NEU": 0.0169487522061296,
        "R_NMC": 0.0157928049010743,
        "R_ASP": -0.07107222240645131,
        "RUS": -0.0470865921199831,
        "MYS": -0.0124924312611528,
        "SWE": 0.00100269164942937,
        "USA": -0.144547884351188,
        "FIN": 0.0119475660939073,
        "COL": -0.0596431620947681,
        "IDN": 0.793150325590199,
        "GBR": -0.00112938898745294
      }
    ],
    "keys": [
      "ARG",
      "AUS",
      "BRA",
      "CAN",
      "CHN",
      "COL",
      "DEU",
      "ETH",
      "FIN",
      "GBR",
      "IDN",
      "IND",
      "MEX",
      "MYS",
      "NOR",
      "RUS",
      "RWA",
      "SWE",
      "USA",
      "ZAF",
      "R_ASP",
      "R_CSA",
      "R_NEU",
      "R_NMC",
      "R_OEU",
      "R_SSA"
    ],
    "byCountry": true,
    "byMultipleCountry": true
  }
]